rvc_py/__init__.py
rvc_py/main.py
rvc_py/root_pipe.py
rvc_py/lib/__init__.py
rvc_py/lib/audio.py
rvc_py/lib/log_config.py
rvc_py/lib/rmvpe.py
rvc_py/lib/infer_pack/__init__.py
rvc_py/lib/infer_pack/attentions.py
rvc_py/lib/infer_pack/commons.py
rvc_py/lib/infer_pack/models.py
rvc_py/lib/infer_pack/modules.py
rvc_py/lib/infer_pack/transforms.py
inf_rvc_py-1.0.0.dist-info/METADATA
inf_rvc_py-1.0.0.dist-info/WHEEL
inf_rvc_py-1.0.0.dist-info/top_level.txt
inf_rvc_py-1.0.0.dist-info/RECORD
