Metadata-Version: 2.1
Name: inf-rvc-py
Version: 1.0.0
Summary: Python wrapper for fast inference with rvc
Home-page: https://github.com/kindahex/rvc-py
Author: kindahex
Requires-Python: >=3.10
Requires-Dist: torch
Requires-Dist: torchaudio
Requires-Dist: gradio
Requires-Dist: praat-parselmouth>=0.4.3
Requires-Dist: pyworld==0.3.2
Requires-Dist: faiss-cpu==1.7.3
Requires-Dist: torchcrepe==0.0.20
Requires-Dist: ffmpeg-python>=0.2.0
Requires-Dist: fairseq==0.12.2
Requires-Dist: typeguard==4.2.0
Requires-Dist: soundfile
Requires-Dist: librosa
Requires-Dist: numpy
Requires-Dist: yt-dlp
Requires-Dist: audio-separator[gpu]
Provides-Extra: all
Requires-Dist: scipy; extra == "all"
Requires-Dist: numba==0.56.4; extra == "all"
Requires-Dist: edge-tts; extra == "all"
